PY_LIB/__init__.py
PY_LIB/core.py
rushitha-0.1.0.dist-info/licenses/LICENSE
rushitha-0.1.0.dist-info/METADATA
rushitha-0.1.0.dist-info/WHEEL
rushitha-0.1.0.dist-info/top_level.txt
rushitha-0.1.0.dist-info/RECORD
