Metadata-Version: 2.4
Name: rushitha
Version: 0.1.0
Summary: A Python package for data analysis and visualization using Pandas, NumPy, Matplotlib, and Seaborn.
Home-page: https://github.com/Rushitha-Kona/pavnds.git
Author: Rushitha Kona
Author-email: rushithakona@gmail.com
Classifier: Programming Language :: Python :: 3
Classifier: License :: OSI Approved :: MIT License
Classifier: Operating System :: OS Independent
Requires-Python: >=3.6
License-File: LICENSE
Requires-Dist: pandas>=1.0
Requires-Dist: numpy>=1.18
Requires-Dist: matplotlib>=3.0
Requires-Dist: seaborn>=0.10
Dynamic: author
Dynamic: author-email
Dynamic: classifier
Dynamic: description
Dynamic: description-content-type
Dynamic: home-page
Dynamic: license-file
Dynamic: requires-dist
Dynamic: requires-python
Dynamic: summary
